mpcontribs/client/__init__.py
mpcontribs_client-5.10.4.dist-info/licenses/LICENSE
mpcontribs_client-5.10.4.dist-info/METADATA
mpcontribs_client-5.10.4.dist-info/WHEEL
mpcontribs_client-5.10.4.dist-info/top_level.txt
mpcontribs_client-5.10.4.dist-info/RECORD
