Metadata-Version: 2.4
Name: mpcontribs-client
Version: 5.10.4
Summary: client library for MPContribs API
Home-page: https://github.com/materialsproject/MPContribs/tree/master/mpcontribs-client
Author: Patrick Huck
Author-email: phuck@lbl.gov
License: MIT
Requires-Python: >=3.8
License-File: LICENSE
Requires-Dist: numpy
Requires-Dist: boltons
Requires-Dist: bravado
Requires-Dist: filetype
Requires-Dist: flatten-dict
Requires-Dist: ipython
Requires-Dist: json2html
Requires-Dist: pandas
Requires-Dist: pint
Requires-Dist: plotly
Requires-Dist: pyIsEmail
Requires-Dist: pymatgen
Requires-Dist: pymongo
Requires-Dist: requests-futures
Requires-Dist: swagger-spec-validator
Requires-Dist: tqdm
Requires-Dist: ujson
Requires-Dist: semantic-version
Requires-Dist: cachetools
Provides-Extra: dev
Requires-Dist: flake8; extra == "dev"
Requires-Dist: pytest; extra == "dev"
Requires-Dist: pytest-flake8; extra == "dev"
Requires-Dist: pytest-pycodestyle; extra == "dev"
Requires-Dist: pytest-cov; extra == "dev"
Requires-Dist: py; extra == "dev"
Dynamic: author
Dynamic: author-email
Dynamic: description
Dynamic: description-content-type
Dynamic: home-page
Dynamic: license
Dynamic: license-file
Dynamic: provides-extra
Dynamic: requires-dist
Dynamic: requires-python
Dynamic: summary
